setup.py
codetiger/__init__.py
codetiger/util/__init__.py
codetiger/util/db.py
codetiger/util/log.py
codetiger_util.egg-info/PKG-INFO
codetiger_util.egg-info/SOURCES.txt
codetiger_util.egg-info/dependency_links.txt
codetiger_util.egg-info/requires.txt
codetiger_util.egg-info/top_level.txt