Metadata-Version: 2.1
Name: codetiger-util
Version: 0.0.3
Summary: 一些python工具类
Home-page: https://gybyt.cn
Author: codetiger
Author-email: admin@gybyt.cn
License: UNKNOWN
Platform: UNKNOWN
